qai/core/__init__.py
qai/core/message.py
qai/core/meta.py
qai/core/t.py
qai/core/utils/__init__.py
qai/core/utils/class_utils.py
qai_core-0.6.0.dist-info/METADATA
qai_core-0.6.0.dist-info/WHEEL
qai_core-0.6.0.dist-info/RECORD
