Metadata-Version: 2.1
Name: qai-core
Version: 0.6.0
Summary: 
Author: parnell
Author-email: 3028114+parnell@users.noreply.github.com
Requires-Python: >=3.11,<4.0
Classifier: Programming Language :: Python :: 3
Classifier: Programming Language :: Python :: 3.11
Classifier: Programming Language :: Python :: 3.12
Requires-Dist: json-fix (>=1.0.0,<2.0.0)
Requires-Dist: pydantic (>=2.7.1,<3.0.0)
Requires-Dist: pytest (>=8.2.1,<9.0.0)
